redislightning/__init__.py
redislightning/example.py
redislightning/redislightning.py
redislightning/redislite_pb2.py
redislightning/redislite_pb2_grpc.py
redislightning-0.2.dist-info/LICENSE
redislightning-0.2.dist-info/METADATA
redislightning-0.2.dist-info/WHEEL
redislightning-0.2.dist-info/top_level.txt
redislightning-0.2.dist-info/RECORD
